{

"label" : "Paris in the Springtime",

"description" : "Historical Fiction Novels Set in Paris",

"list" : [
  
{  

"label" : "All the Flowers in Paris",

"isbns" : [

"9781101885055",

"9781643583471"

]

},

{

"label" : "All the Ways we Said Goodbye  of the Ritz Paris",

"isbns" : [

"9780062931092"

]

},

{

"label" : "Enchantress of Paris of the Sun King's Court",

"isbns" : [


"9781250057099"

]

},

{

"label" : "Last Christmas in Paris of World War I",

"isbns" : [

"9780062836267",

"9780062562685",

"9780062562685"

]

},

{

"label" : "Lovers at the Chameleon Club, Paris 1932",

"isbns" : [

"9780061713781"

]

},

{

"label" : "Mission to Paris"

"isbns" : [

"9781400069484",

"9780679604228",

"9780679604228"

]

},

{

"label" : "Moonlight Over Paris",

"isbns" : [

"9780062389824"

]

},

{

"label" : "Paris : the novel",

"9780385535304",

"9780385359542",

"9780385359542",

"9780385535311",

"9780385535311"

]

},

{

"label" : "Paris, 7 a.m.",

"isbns" : [

"9781501197215"

]

},

{

"label" : "The Last Time I Saw Paris",

"isbns" : [

"9780786234363"

]

},

{

"label" : "The Lost Girls of Paris",

"isbns" : [

"9781489276254",

"9781489276254",

"9781432858773"

]

},

{

"label" : "The Paris Architect",

"isbns" : [

"9780804190848",

"9781402284335",

"9781402284335"

]

},

{

"label" : "The Paris Orphan",

"9781538764893",

"9781538764916",

"9781432877132"

]

},

{

"label" : "The Paris Seamstress",

"isbns" : [

"9781538714775",

"9781549146039"

]

},

{

"label" : "The Paris Spy : a Maggie Hope mystery",

"isbns" : [

"9780399593802",

"9781524782382",

"9780399593819"

]

},

{

"label" : "The Paris Wife",

"isbns" : [

"9780345521309",

"9780307877185",

"9780345521309"

]

},

{

"label" : "The Paris Winter",

"isbns" : [

"9781250051837",

"9781427251961"

]

},

{

"label" : "The Parisian, or, al-Barisi",

"isbns" : [

"9780802129437"

]

},

{

"label" : "The Race for Paris",

"isbns" : [

"9780062354631",

]

}

]

}
